README.txt
setup.py
collective/__init__.py
collective.novate.egg-info/PKG-INFO
collective.novate.egg-info/SOURCES.txt
collective.novate.egg-info/dependency_links.txt
collective.novate.egg-info/entry_points.txt
collective.novate.egg-info/namespace_packages.txt
collective.novate.egg-info/not-zip-safe
collective.novate.egg-info/requires.txt
collective.novate.egg-info/top_level.txt
collective/novate/__init__.py
collective/novate/browser.py
collective/novate/interfaces.py