Metadata-Version: 1.0
Name: collective.novate
Version: 1.0b3
Summary: Adds an option too reassign ownership on the sharing page
Home-page: http://pypi.python.org/pypi/collective.novate
Author: Martin Aspeli
Author-email: optilude@gmail.com
License: GPL
Keywords: plone ownership sharing
Platform: UNKNOWN
Classifier: Framework :: Plone
Classifier: Programming Language :: Python
Classifier: Topic :: Software Development :: Libraries :: Python Modules
